README.md
setup.cfg
setup.py
bymtesting/__init__.py
bymtesting/sandboxt.py
bymtesting/setPYTHONPATH.bat
bymtesting/setup_test_workplace.py
bymtesting/sysPathHanlder.py
bymtesting.egg-info/PKG-INFO
bymtesting.egg-info/SOURCES.txt
bymtesting.egg-info/dependency_links.txt
bymtesting.egg-info/entry_points.txt
bymtesting.egg-info/requires.txt
bymtesting.egg-info/top_level.txt
bymtesting/Autentisering/AutentiseringService.py
bymtesting/Autentisering/AutentiseringServiceInfo.py
bymtesting/Autentisering/AutentiseringServicePayload.py
bymtesting/Autentisering/AutentiseringSetupService.py
bymtesting/Autentisering/AutentiseringUrlService.py
bymtesting/Autentisering/__init__.py
bymtesting/Autorisasjon/ActualDictionaryService.py
bymtesting/Autorisasjon/ExcelService.py
bymtesting/Autorisasjon/__init__.py
bymtesting/Cache/CachingForTestCase.py
bymtesting/Cache/DockerTestCacheService.py
bymtesting/Cache/__init__.py
bymtesting/Lib/Api.py
bymtesting/Lib/EnvironmentService.py
bymtesting/Lib/Exceptions.py
bymtesting/Lib/JsonBase.py
bymtesting/Lib/RequestService.py
bymtesting/Lib/ServiceBase.py
bymtesting/Lib/ServiceBasePayload.py
bymtesting/Lib/SwaggerService.py
bymtesting/Lib/__init__.py
bymtesting/Seed/SeedDataTemplate.py
bymtesting/Seed/SeedDatabase.py
bymtesting/Seed/SeedDatabaseServiceData.py
bymtesting/Seed/__init__.py
bymtesting/Tests/Template.py
bymtesting/Tests/__init__.py
bymtesting/WebApi/LoginService.py
bymtesting/WebApi/UrlService.py
bymtesting/WebApi/WebApiFactoryService.py
bymtesting/WebApi/WebApiService.py
bymtesting/WebApi/WebApiServiceBasePayload.py
bymtesting/WebApi/WebApiServiceInfo.py
bymtesting/WebApi/WebApiSetupService.py
bymtesting/WebApi/__init__.py