Metadata-Version: 1.1
Name: bymtesting
Version: 1.0.3
Summary: A python framework for integrtion testing av asp.net core web apies.
Home-page: https://bitbucket.org/dkezri/bympythonframework
Author: Oslo Kommune Bymiljøetaten
Author-email: diako.k@gmail.com
License: Bym-developers
Download-URL: https://bitbucket.org/dkezri/bympythonframework/get/1.0.3.tar.gz
Keywords: testing,integrationTesting,webapi testing
Platform: UNKNOWN
